{
    "PAGE_TITLE": "Забрана корисника - FastComments",
    "HEADING": "Забрана приступа кориснику",
    "SUB_HEADING": "Забрана приступа кориснику путем имејла",
    "INTRO_DESCRIPTION": "Овде можете унети имејл адресу којом желите да забраните корисника. Постоји неколико начина да забраните корисника. Трајно забрањивање корисника му никада неће дозволити да гласа или коментарише, и одмах ће знати када покуша да коментарише јер ће га обавестити систем. Затајено забрањивање ће учинити да изгледа као да су његови гласови или коментари успешни, али неће трајати.",
    "ENTER_EMAIL_HEADING": "Унесите имејл адресу",
    "EMAIL_LABEL": "Е-пошта",
    "TYPE_LABEL": "Тип",
    "TYPE_BAN": "Забрана",
    "TYPE_SHADOW_BAN": "Забрана сенке",
    "DURATION_LABEL": "Трајање",
    "DURATION_FOREVER": "Заувек",
    "DURATION_ONE_HOUR": "Један сат",
    "DURATION_ONE_DAY": "Један дан",
    "DURATION_ONE_WEEK": "Једна недеља",
    "DURATION_ONE_MONTH": "Један месец",
    "DURATION_SIX_MONTHS": "Шест месеци",
    "DURATION_ONE_YEAR": "Једна година",
    "BAN_USER_BUTTON": "Забрани кориснику"
}