{
    "PAGE_TITLE": "Webhooks - FastComments",
    "HEADING": "网络钩子",
    "WEBHOOK_LOGS_LINK": "Webhook 日志",
    "DOCUMENTATION_LINK_TEXT": "有关文档和请求结构，请参见<a href=\"https://docs.fastcomments.com/guide-webhooks.html\" target=\"_blank\">此处</a>。",
    "NOSCRIPT_MESSAGE": "此用户界面需要 JavaScript 才能正常运行。",
    "CONFIGURE_DOMAIN_LABEL": "配置域",
    "ALL_DOMAINS_OPTION": "所有域名",
    "RECENT_FAILURES_NOTIFICATION": "❗ 近期 Webhook 故障",
    "RECENT_FAILURES_MESSAGE": "您最近有多次 webhook 请求失败的情况。请尝试查看日志。",
    "ON_COMMENT_CREATED_LABEL": "评论已创建",
    "ON_COMMENT_UPDATED_LABEL": "评论已更新",
    "ON_COMMENT_DELETED_LABEL": "评论已删除",
    "IDEMPOTENT_OPERATION_TITLE": "这是一个幂等运算。",
    "SAVE_BUTTON": "节省",
    "URL_PLACEHOLDER": "https://your-site.com/your-endpoint",
    "SEND_TEST_PAYLOAD_BUTTON": "发送测试有效载荷",
    "STATUS_VERIFIED": "✔️ 已验证",
    "STATUS_NOT_VERIFIED": "❌ 未经核实。",
    "STATUS_NOT_VERIFIED_EXPECTED_200": "❌ 未验证。预期状态码为 200。",
    "STATUS_NOT_VERIFIED_EXPECTED_401": "❌ 未验证。API密钥无效时，预期状态码为401。",
    "STATUS_YOU_PROVIDED": "您提供了[statusCode]。",
    "BUTTON_SET_READY": "准备就绪",
    "BUTTON_SET_NOT_READY": "设置尚未就绪",
    "CONFIRM_SET_READY": "这将手动将 webhook 状态设置为“就绪”，绕过 API 密钥验证。是否继续？",
    "EVENTS_IN_QUEUE": "队列中已处理[count]事件。",
    "INTRO_TEXT": "FastComments 支持评论的 Webhook。所有有效负载均使用 HMAC 签名进行签名。您可以在下方全局配置 Webhook，也可以针对特定域进行配置。",
    "INCLUDE_API_KEY_LABEL": "包含 API 密钥（旧版）",
    "TEST_STATUS_NO_URL": "请先输入网址。",
    "TEST_STATUS_SUCCESS": "✔️ 测试载荷已发送！状态：[statusCode]",
    "TEST_STATUS_FAILED": "❌ 测试载荷失败。状态：[statusCode]",
    "TEST_STATUS_ERROR": "❌ 测试载荷发送失败。"
}