{
    "INTRO": "Здравей <%= username %>, спечелил си нова значка!",
    "CONGRATULATIONS": "Поздравления!",
    "BANNER_TEXT": "Спечелена нова значка",
    "FROM_NAME": "Робот за бързи коментари",
    "SUBJECT": "Спечелихте значката „<%= badge.displayLabel %>“!",
    "BADGE_EARNED_MESSAGE": "Успешно спечелихте <strong><%= badge.displayLabel %></strong> значката.",
    "KEEP_UP_GOOD_WORK": "Продължавай с отличната работа!",
    "UNSUBSCRIBE_HERE": "Отписване от известия за значки",
    "VIEW_YOUR_PROFILE": "Преглед на профила ви"
}