{
    "TITLE": "Код моей учетной записи",
    "OTHER_WIDGETS": "Другие виджеты",
    "HEADING": "Код виджета комментариев",
    "ADD_TO_WEBSITE": "Добавить FastComments на сайт",
    "COPY_CODE_DESCRIPTION": "Скопируйте следующий код на веб-страницу, чтобы создать экземпляр FastComments.",
    "DOCUMENTATION": "Документация",
    "EXTENSION_LINK": "Комментарии не отображаются? Попробуйте наше <a href=\"https://chrome.google.com/webstore/detail/fastcomments-debugger/cadggdemhfkjjghkdbfhonoccnplffjj\" target=\"_blank\">расширение для Chrome</a> .",
    "SHOW_ADVANCED_OPTIONS": "Показать дополнительные параметры",
    "ADVANCED_DOCUMENTATION_HEADING": "Документация",
    "ADVANCED_OPTIONS_NOTE": "Обратите внимание, что некоторые из этих расширенных параметров можно легко настроить с помощью ссылки «Настроить» в правом верхнем углу, то есть программирование не требуется.",
    "CODE_TABBED_NPM_INSTALL_REACT": "npm install --save fastcomments-react",
    "CODE_TABBED_NPM_INSTALL_VUE": "npm install --save fastcomments-vue",
    "CODE_TABBED_SEE_INSTALLATION_ANGULAR": "Инструкции по установке см. на сайте npmjs.com.",
    "CODE_TABBED_DEMO_TEXT": "Скрипт предназначен только для демонстрационных целей. Чтобы получить фрагмент для использования в рабочей среде, создайте учетную запись.",
    "CODE_TABBED_VANILLAJS": "VanillaJS",
    "CODE_TABBED_ANGULAR": "Угловой",
    "CODE_TABBED_REACT": "Реакции",
    "CODE_TABBED_VUE": "Вью",
    "CODE_TABBED_VANILLAJS_LOGO": "Логотип VanillaJS",
    "CODE_TABBED_ANGULAR_LOGO": "Угловой логотип",
    "CODE_TABBED_REACT_LOGO": "Логотип ReactJS",
    "CODE_TABBED_VUE_LOGO": "Логотип VueJS"
}