{
    "PAGE_TITLE": "Συνδέστε το κατάστημά σας - FastComments",
    "STEP_LABEL": "Βήμα 2 από 3",
    "WHAT_HAPPENS_HEADING": "Τι συμβαίνει στη συνέχεια;",
    "DESCRIPTION": "Εντοπίσαμε το κατάστημά σας στο Shopify. Για να ενεργοποιήσετε τα σχόλια στις σελίδες του καταστήματός σας, πρέπει να το συνδέσουμε με τον λογαριασμό σας στο FastComments.",
    "META_DESCRIPTION": "Συνδέστε το κατάστημά σας στο Shopify με τον λογαριασμό σας στο FastComments.",
    "HEADING": "Συνδέστε το κατάστημά σας",
    "DOMAIN_LABEL": "Αποθηκεύστε για σύνδεση",
    "BUTTON_CONNECT": "Συνδέστε το κατάστημα",
    "WHAT_HAPPENS_TEXT": "Μόλις συνδεθεί, θα λάβετε ένα αναγνωριστικό ενοικιαστή για να το επικολλήσετε στα μπλοκ θέματος του Shopify. Αυτό είναι όλο, τα σχόλια θα εμφανίζονται στο κατάστημά σας.",
    "MANAGE_DOMAINS_LINK_TEXT": "Ρύθμιση παραμέτρων τομέων",
    "MANAGE_DOMAINS_NOTE": "Μπορείτε να διαχειριστείτε τους συνδεδεμένους τομείς σας οποιαδήποτε στιγμή από"
}