{
    "PAGE_TITLE": "Помилка входу",
    "HERO_TITLE_LIGHT": "Вхід ",
    "HERO_TITLE_BOLD": "Не вдалося",
    "HERO_DESCRIPTION": "З якоїсь причини ви не змогли увійти. Будь ласка, спробуйте пізніше.",
    "BUTTON_TRY_AGAIN": "Спробуйте ще раз",
    "LINK_VALIDITY_MESSAGE": "Можливо, це посилання більше недійсне? Зверніть увагу, що посилання для входу можна використовувати лише один раз, після чого вони втрачають свою чинність з міркувань безпеки. Нові посилання також замінюють старі — переконайтеся, що це найновіше посилання!"
}