{
    "INTRO": "Zdravo<%= displayName %>",
    "NEW_REFERRAL": "Imate novu preporuku!",
    "NEW_REFERRAL_DETAILS": "Pomenuli ste <%= referredTenantName %>. Na osnovu njihove trenutne konfiguracije, zaradićete <%= displayCommission %> svakog meseca.",
    "BANNER_TEXT": "Novi FastComments Referenцa",
    "FROM_NAME": "FastComments upućivanje robot",
    "SUBJECT": "Novi FastComments Referenцa",
    "THANKS_FOR_CHOOSING_FC": "Hvala što ste izabrali FastComments.com.",
    "UNSUBSCRIBE_FROM_THESE_ALERTS": "Odjavite se sa ovih upozorenja."
}