{
    "PAGE_TITLE": "Adicionar um domínio - FastComments",
    "HEADING_USER_ACCOUNT": "Conta de <%= user.username %>",
    "HEADING_ADD_DOMAINS": "Adicionar domínios",
    "TEXT_ADD_DOMAIN_INFO": "Adicionar um domínio permite que você personalize seus widgets e interações do usuário por site. Também nos permite validar as solicitações e vinculá-las à sua conta.",
    "LABEL_DOMAIN_NAME": "Nome de domínio",
    "PLACEHOLDER_DOMAIN_NAME": "Insira um domínio de nível superior, como fastcomments.com. Use um subdomínio para restringir ainda mais o acesso, se desejar.",
    "TEXT_COMMA_SEPARATED_NOTE": "Você pode inserir domínios em formato separado por vírgulas.",
    "TEXT_DOMAIN_VALID": "✔️ <%= domain.domain %>",
    "TEXT_DOMAIN_INVALID": "❌ \"<%= domain.input %>\": <%= domain.reason %>",
    "BUTTON_SAVE": "Salvar"
}