{
    "FEED_EMPTY": "暂无帖子。",
    "FEED_NEW_POST_BANNER": "显示[count]新帖子",
    "FEED_COMPOSER_TITLE_PLACEHOLDER": "标题（可选）",
    "FEED_SUBMIT_POST": "邮政",
    "FEED_COMPOSER_CONTENT_PLACEHOLDER": "分享一些东西……",
    "FEED_FOLLOW": "跟随",
    "FEED_NEW_POST_BANNER_PLURAL": "显示[count]新帖子",
    "FEED_FOLLOWING": "下列的",
    "FEED_MEDIA_ATTACH": "添加图片",
    "FEED_LOAD_FAILED": "无法加载信息源，请稍后再试。",
    "FEED_MEDIA_REMOVE": "消除",
    "FEED_MEDIA_UPLOADING": "正在上传...",
    "FEED_REACTION_PICK": "React",
    "FEED_REACTION_LAUGH": "笑",
    "FEED_REACTION_SAD": "伤心",
    "FEED_REACTION_THUMBS_UP": "竖起大拇指",
    "FEED_MEDIA_UPLOAD_FAILED": "图片上传失败。",
    "FEED_REACTION_HEART": "心",
    "FEED_REACTION_ANGRY": "生气的",
    "FEED_REACTION_WOW": "哇",
    "FEED_REACTION_FAILED": "无法保存反应。请重试。"
}