{
    "PAGE_TITLE": "Courriels supprimés - FastComments",
    "HEADING": "Courriels supprimés",
    "INFO_NOTE": "Les adresses électroniques listées ici ont été bloquées par le fournisseur de messagerie en raison de retours à l'expéditeur, de plaintes ou de désabonnements. Ces adresses ne recevront plus aucun courriel tant que le blocage persistera.",
    "FILTER_LABEL_EMAIL": "Filtrer par e-mail",
    "FILTER_PLACEHOLDER_EMAIL": "Rechercher un e-mail...",
    "FILTER_LABEL_PROVIDER": "Fournisseur",
    "FILTER_OPTION_ALL": "Tous les fournisseurs",
    "FILTER_BUTTON": "Filtre",
    "TABLE_HEADER_EMAIL": "E-mail",
    "TABLE_HEADER_PROVIDER": "Fournisseur",
    "TABLE_HEADER_TYPE": "Taper",
    "TABLE_HEADER_REASON": "Raison",
    "TABLE_HEADER_DATE": "Date",
    "TABLE_HEADER_ACTIONS": "Actes",
    "BUTTON_REMOVE": "Retirer",
    "BUTTON_PREVIOUS": "Précédent",
    "BUTTON_NEXT": "Suivant",
    "EMPTY_STATE": "Aucun e-mail supprimé n'a été trouvé pour votre compte.",
    "EMPTY_STATE_FILTERED": "Aucun courriel supprimé ne correspond à votre filtre.",
    "SUCCESS_REMOVED": "La suppression a été effectuée avec succès. L'adresse e-mail peut à nouveau recevoir des e-mails.",
    "ERROR_REMOVE_FAILED": "Impossible de supprimer le blocage auprès de votre fournisseur de messagerie. Veuillez réessayer plus tard.",
    "RATE_LIMIT_MONTHLY": "Limite de suppressions mensuelles atteinte (5 par mois). Veuillez réessayer le mois prochain.",
    "RATE_LIMIT_RECENTLY_REMOVED": "Récemment supprimé",
    "REMOVALS_USED": "Déménagements effectués ce mois-ci :",
    "REMOVALS_OF": "de",
    "PAGE_LABEL": "Page"
}