{
    "PAGE_TITLE": "Eliminazione della configurazione LTI - FastComments",
    "HEADING": "Elimina la configurazione LTI",
    "DELETE_HEADING": "Conferma l'eliminazione",
    "LABEL_NAME": "Nome",
    "LABEL_PLATFORM": "Piattaforma",
    "BUTTON_CANCEL": "Annulla",
    "LABEL_ISSUER": "Emittente",
    "BUTTON_CONFIRM_DELETE": "Elimina",
    "LABEL_CLIENT_ID": "ID client",
    "DELETE_DESCRIPTION": "Sei sicuro di voler eliminare questa configurazione LTI? Gli avvii esistenti smetteranno di funzionare."
}