{
    "PAGE_TITLE": "Medien - Schnellkommentare",
    "HEADING_MEDIA": "Medien",
    "TEXT_DRAG_DROP": "Ziehen Sie Bilder per Drag & Drop hierher oder klicken Sie, um Dateien auszuwählen.",
    "BTN_CHOOSE_FILES": "Dateien auswählen",
    "TEXT_NO_MEDIA": "Es wurden noch keine Medien hochgeladen.",
    "TEXT_UPLOADING": "Wird hochgeladen...",
    "TEXT_UPLOAD_FAILED": "Der Upload ist fehlgeschlagen. Bitte versuchen Sie es erneut.",
    "TEXT_DELETE_CONFIRM": "Möchten Sie dieses Bild wirklich löschen?",
    "BTN_DELETE": "Löschen",
    "BREADCRUMB_SITES": "Websites",
    "NAV_BUILDER": "Bauherr",
    "NAV_COLLECTIONS": "Sammlungen",
    "NAV_THEME": "Thema",
    "NAV_SETTINGS": "Einstellungen",
    "NAV_MEMBERSHIPS": "Mitgliedschaften",
    "NAV_MEMBERS": "Mitglieder",
    "NAV_MEDIA": "Medien",
    "NAV_VIEW_PUBLIC": "Sicht"
}