{
    "PAGE_TITLE": "Kullanıcı Adını Unuttum - FastComments",
    "HERO_TITLE_LIGHT": "Unutmuş olmak  ",
    "HERO_TITLE_BOLD": "Kullanıcı adı",
    "HERO_DESCRIPTION": "Hiç endişelenmeyin, en iyilerimizin bile başına gelir!",
    "LABEL_EMAIL": "E-posta",
    "EMAIL_HELP_TEXT": "Kullanıcı adınızı size e-posta yoluyla göndereceğiz. Güvenlik nedenleriyle e-posta adresinizin doğru olup olmadığını size bildiremiyoruz.",
    "LABEL_CAPTCHA": "<%= captchaA %> + <%= captchaB %> nedir?",
    "CAPTCHA_HELP": "Bot olmadığınızı belirlemeye yardımcı olur.",
    "BUTTON_REQUEST_USERNAME": "Kullanıcı Adı Talebi",
    "SUCCESS_MESSAGE": "Eğer o e-posta adresinde bir hesabınız varsa, kısa süre içinde kullanıcı adınızın yer aldığı bir e-posta alacaksınız.",
    "SUCCESS_CHECK_SPAM": "Lütfen spam klasörünüzü kontrol etmeyi unutmayın.",
    "SUCCESS_CLOSE_WINDOW": "Şimdi bu pencereyi kapatabilirsiniz."
}