{
    "PAGE_TITLE": "Kullanıcıyı Davet Et - FastComments",
    "HEADING": "Bir Yöneticiyi Davet Et",
    "MESSAGE_INVITE_DESCRIPTION": "Şu anda yorumcu olan bir kullanıcıyı yönetici olmaya davet etmek, hesabını yönetici statüsüne yükseltecek ve onu kiracınıza ekleyecektir.",
    "MESSAGE_CONFIRM_USERNAME": "<b>&quot;<%= invitingUserName %>&quot; kullanıcı adına sahip kullanıcıyı ekleyeceksiniz. Lütfen bunun doğru olduğundan emin olun.</b>",
    "HEADING_PERMISSIONS": "İzinler",
    "MESSAGE_PERMISSIONS": "Daveti kabul ettiklerinde hangi yetkilere sahip olmalarını istersiniz?",
    "BUTTON_SEND_INVITE": "Davetiye Gönder"
}