{
    "PAGE_TITLE": "I miei biglietti - FastComments",
    "HEADING": "Supporto FastComments",
    "HEADING_CREATE": "Crea un ticket",
    "MESSAGE_CREATE_INSTRUCTIONS": "Quale dovrebbe essere il titolo del tuo ticket? Ti mostreremo alcuni articoli pertinenti dalla nostra documentazione e, se non trovi nulla di pertinente, potrai creare un ticket.",
    "PLACEHOLDER_SEARCH": "Inserisci il titolo del biglietto",
    "NOSCRIPT_SEARCH": "Questa funzione di ricerca richiede JavaScript.",
    "LOADING": "Caricamento...",
    "HEADING_MY_TICKETS": "I miei biglietti",
    "TABLE_HEADER_ID": "ID",
    "TABLE_HEADER_SUBJECT": "Soggetto",
    "TABLE_HEADER_CREATED_BY": "Creato da",
    "TABLE_HEADER_LAST_REPLY": "Ultima risposta",
    "TABLE_HEADER_STATUS": "Stato",
    "MESSAGE_NO_TICKETS": "Non hai ancora nessun biglietto!",
    "VALUE_DELETED": "(eliminato)",
    "VALUE_NONE": "Nessuno",
    "STATUS_AWAITING_REPLY": "IN ATTESA DELLA TUA RISPOSTA"
}