{
    "SHOWING_COMMENTS": "<%= Number((page - 1) * count).toLocaleString() %> - <%= Number(((page - 1) * count) + comments.length).toLocaleString() %> を表示",
    "SELECT_ALL_LABEL": "すべて選択",
    "CONFIRM_REMOVAL_MESSAGE": "このコメントを削除してもよろしいですか?",
    "CONFIRM_REMOVAL_BUTTON": "削除の確認",
    "CANCEL_REMOVAL_BUTTON": "キャンセル",
    "RESET_FLAG_MESSAGE": "このコメントのフラグ数をリセットしてもよろしいですか?",
    "RESET_FLAG_NOTE": "このコメントにフラグを立てたユーザーには影響しません。",
    "RESET_FLAG_BUTTON": "フラグカウントをリセット",
    "CANCEL_FLAG_BUTTON": "キャンセル",
    "BAN_USER_MESSAGE": "このユーザーを禁止するにはどうすればいいですか?",
    "BAN_VIA_EMAIL_ACCOUNT_LABEL": "メール/アカウントによる禁止",
    "ANONYMOUS_COMMENT_NOTE": "これは匿名のコメントです。禁止できるメールアドレスやアカウントはありません。",
    "BAN_VIA_IP_LABEL": "IP経由の禁止",
    "BAN_EMAIL_DOMAIN_LABEL": "すべての<%= comment.commenterEmail.substring(comment.commenterEmail.indexOf('@'), comment.commenterEmail.length) %>ユーザーを禁止する",
    "BAN_TYPE_LABEL": "禁止タイプ",
    "BAN_TYPE_BAN": "禁止",
    "BAN_TYPE_SHADOW_BAN": "シャドウバン",
    "BAN_DURATION_LABEL": "禁止期間",
    "DURATION_FOREVER": "永遠に",
    "DURATION_ONE_HOUR": "1時間",
    "DURATION_ONE_DAY": "ある日",
    "DURATION_ONE_WEEK": "1週間",
    "DURATION_ONE_MONTH": "1ヶ月",
    "DURATION_SIX_MONTHS": "6ヶ月",
    "DURATION_ONE_YEAR": "1年",
    "DELETE_ALL_COMMENTS_LABEL": "<%= comment.commenterName ? comment.commenterName : 'Anonymous' %> のコメントをすべて削除します。",
    "BAN_DELETES_COMMENT_NOTE": "このユーザーを禁止すると、このコメントも削除されます。",
    "CONFIRM_BAN_BUTTON": "禁止を確認",
    "CANCEL_BAN_BUTTON": "キャンセル",
    "PREV_BUTTON": "前へ",
    "NEXT_BUTTON": "次",
    "NO_COMMENTS_HEADING": "まだコメントはありません!",
    "NO_COMMENTS_MESSAGE": "まだコメントがないようです。",
    "ADD_FASTCOMMENTS_LINK": "ウェブサイトにFastCommentsを追加する",
    "NOTHING_TO_SEE_HEADING": "ここには何もありません",
    "ADJUST_FILTERS_MESSAGE": "フィルターを調整してみてください。",
    "NEEDS_REVIEW_NOTE": "注意: 管理者またはモデレーターによる新しいコメントは、「レビューが必要」の下には表示されません。"
}