{
    "PAGE_TITLE_ADD": "Dodajte korisnika - FastComments",
    "PAGE_TITLE_EDIT": "Edit <%= editingUser.username %> - FastComments",
    "HEADING_ADD": "Dodajte korisnika",
    "HEADING_EDIT": "Uredi <%= editingUser.username %>",
    "SUBHEADING_ADD": "Dodavanje korisnika",
    "SUBHEADING_EDIT": "Uređivanje <%= editingUser.username %>",
    "LABEL_AVATAR": "Avatar",
    "BUTTON_SET_AVATAR": "Kliknite da biste podesili svoj avatar",
    "BUTTON_UPDATE_AVATAR": "Kliknite da biste ažurirali svoj avatar",
    "HELP_AVATAR_SIZE": "Maksimalna veličina: KSNUMKSmb",
    "LABEL_USERNAME": "Korisničko ime",
    "PLACEHOLDER_USERNAME": "super-osoba-2",
    "LABEL_EMAIL": "E-pošta",
    "PLACEHOLDER_EMAIL": "email@example.com",
    "LABEL_LOCALE": "Lokacija",
    "LABEL_PERMISSIONS": "Dozvole",
    "BUTTON_SUBMIT": "Pretraga",
    "USERNAME_EXISTS_SAME_TENANT": "❗ Korisnik sa tim korisničkim imenom već postoji za ovog stanara.",
    "USERNAME_EXISTS_INVITE": "❗ Korisnik FastComments sa tim korisničkim imenom već postoji, ali ne i za ovog stanara. Da li želite da ih <a href=\"{{INVITE_URL}}\">pozovete</a>?",
    "USERNAME_EXISTS_OTHER_TENANT": "❌ Korisnik FastComments sa tim korisničkim imenom već postoji za drugog stanara.",
    "USERNAME_AVAILABLE": "✔️ To korisničko ime je dostupno.",
    "EMAIL_EXISTS_SAME_TENANT": "❗ Korisnik sa tom e-poštom već postoji za ovog stanara.",
    "EMAIL_EXISTS_INVITE": "❗ Korisnik FastComments sa tom e-poštom već postoji, ali ne i za ovog stanara. Da li želite da ih <a href=\"{{INVITE_URL}}\">pozovete</a>?",
    "EMAIL_EXISTS_OTHER_TENANT": "❌ Korisnik FastComments sa tom e-poštom već postoji za drugog stanara.",
    "EMAIL_AVAILABLE": "✔️ Taj e-mail je dostupan."
}