{
    "TITLE": "Instalar FastComments",
    "HEADS_UP": "¡Aviso!",
    "COMMENTER_ACCOUNT_WARNING": "¡Esta cuenta es solo para dejar comentarios! Antes de añadir FastComments a un sitio web, <a href=\"/traffic-pricing\" target=\"_blank\">selecciona un plan para comenzar tu prueba gratuita</a> .",
    "INSTALLATION_WIZARD_VIEWING_FOR": "Instrucciones de visualización para [productName].",
    "INSTALLATION_WIZARD_CHANGE": "Cambiar.",
    "PAGE_SUBTITLE_SELECT_PRODUCT": "Seleccione un producto para comenzar.",
    "PAGE_TITLE_PICK_INTEGRATION": "Elija una integración.",
    "PAGE_TITLE_PICK_FRAMEWORK": "Elige tu marco.",
    "PAGE_TITLE_NOT_FOUND": "Extraviado",
    "PAGE_TITLE_SETUP": "Configuración [frameworkId]",
    "PRODUCT_NOT_FOUND": "Ese producto no fue encontrado",
    "SECTION_DOCUMENTATION": "Documentación",
    "SECTION_OTHER_WIDGETS": "Otros widgets",
    "SECTION_FRONTEND_FRAMEWORKS": "Frameworks y bibliotecas frontend.",
    "SECTION_BACKEND_FRAMEWORKS": "Ejemplos de frameworks de backend",
    "SECTION_NOTE_RETURN": "Nota: Puedes volver a esta página desde Ajustes ➔ Instalar.",
    "BUTTON_GET_STARTED": "Empezar",
    "BUTTON_EXPLORE_DOCS": "Explorar documentos",
    "BUTTON_GET_CODE": "Obtener código",
    "BUTTON_SELECT": "Seleccionar",
    "BUTTON_SEE_EXAMPLES": "Ver ejemplos",
    "PRODUCT_LIVE_COMMENTING_LABEL": "Comentarios en vivo",
    "PRODUCT_LIVE_COMMENTING_DESCRIPTION": "<b>Comentarios en vivo</b> personalizables para cualquier página o aplicación.",
    "PRODUCT_STREAM_CHAT_LABEL": "Chat en directo",
    "PRODUCT_STREAM_CHAT_DESCRIPTION": "<b>Chat en streaming</b> para cualquier página o aplicación.",
    "PRODUCT_IMAGE_CHAT_LABEL": "Chat de imágenes",
    "PRODUCT_IMAGE_CHAT_DESCRIPTION": "Añadir conversaciones a <b>las imágenes</b> .",
    "PRODUCT_COLLAB_CHAT_LABEL": "Chat de colaboración",
    "PRODUCT_COLLAB_CHAT_DESCRIPTION": "<b>Resaltar</b> y discutir fragmentos de <b>texto</b> .",
    "DOC_CUSTOMIZE_LABEL": "Personalizar FastComments",
    "DOC_CUSTOMIZE_DESCRIPTION": "Aprenda a personalizar FastComments.",
    "DOC_MODERATING_LABEL": "Moderación de comentarios",
    "DOC_MODERATING_DESCRIPTION": "Descubra cómo funciona la moderación con FastComments.",
    "DOC_API_LABEL": "API",
    "DOC_API_DESCRIPTION": "Conéctese a FastComments.",
    "DOC_ALL_LABEL": "Toda la documentación",
    "DOC_ALL_DESCRIPTION": "Explora los documentos.",
    "DOC_INSTALL_LABEL": "Instalar FastComments",
    "DOC_INSTALL_DESCRIPTION": "Aprenda cómo instalar FastComments.",
    "WIDGET_BULK_COMMENT_COUNT_LABEL": "Recuento de comentarios masivos",
    "WIDGET_BULK_COMMENT_COUNT_DESCRIPTION": "Muestra de forma eficiente el número de comentarios de muchos hilos a la vez.",
    "WIDGET_COMMENT_COUNT_LABEL": "Recuento de comentarios",
    "WIDGET_COMMENT_COUNT_DESCRIPTION": "Añade un recuento de comentarios a cualquier página.",
    "WIDGET_PAGE_REACTS_LABEL": "Reacciones de la página",
    "WIDGET_PAGE_REACTS_DESCRIPTION": "Añade un botón flotante de “Me gusta” a cualquier página.",
    "WIDGET_RECENT_COMMENTS_LABEL": "Comentarios recientes",
    "WIDGET_RECENT_COMMENTS_DESCRIPTION": "Añade una lista de comentarios recientes a cualquier página.",
    "WIDGET_TOP_PAGES_LABEL": "Páginas principales",
    "WIDGET_TOP_PAGES_DESCRIPTION": "Agregue una lista de las páginas principales, por cantidad de comentarios, a cualquier página.",
    "INTEGRATION_CUSTOM_LABEL": "Costumbre",
    "INTEGRATION_CUSTOM_DESCRIPTION": "Instala FastComments como quieras, en cualquier sitio o aplicación.",
    "INTEGRATION_WORDPRESS_LABEL": "WordPress",
    "INTEGRATION_WORDPRESS_DESCRIPTION": "Complemento propio disponible.",
    "INTEGRATION_WIX_LABEL": "Wix",
    "INTEGRATION_WIX_DESCRIPTION": "Añade comentarios en vivo a tu sitio Wix.",
    "INTEGRATION_BIGCOMMERCE_LABEL": "Gran comercio",
    "INTEGRATION_BIGCOMMERCE_DESCRIPTION": "Agregue comentarios en vivo a su tienda o blog de BigCommerce.",
    "INTEGRATION_BUBBLEIO_LABEL": "Burbuja.io",
    "INTEGRATION_BUBBLEIO_DESCRIPTION": "Agregue comentarios en vivo a su sitio Bubble.io.",
    "INTEGRATION_IONOS_LABEL": "Ionos",
    "INTEGRATION_IONOS_DESCRIPTION": "Añade comentarios en vivo a tu sitio Ionos.",
    "INTEGRATION_GODADDY_LABEL": "GoDaddy",
    "INTEGRATION_GODADDY_DESCRIPTION": "Añade comentarios en vivo a tu sitio de GoDaddy.",
    "INTEGRATION_FRAMER_LABEL": "Enmarcador",
    "INTEGRATION_FRAMER_DESCRIPTION": "Agregue comentarios en vivo a su sitio Framer.",
    "INTEGRATION_SQUARESPACE_LABEL": "Espacio cuadrado",
    "INTEGRATION_SQUARESPACE_DESCRIPTION": "Agregue comentarios en vivo a su sitio SquareSpace.",
    "INTEGRATION_SUPERSO_LABEL": "Súper.so",
    "INTEGRATION_SUPERSO_DESCRIPTION": "Añade discusiones en vivo a tu sitio Super.so.",
    "INTEGRATION_SYSTEME_LABEL": "Systeme.io",
    "INTEGRATION_SYSTEME_DESCRIPTION": "Agregue comentarios en vivo a su blog o sitio de Systeme.io.",
    "INTEGRATION_CLICKFUNNELS_LABEL": "Embudos de clic",
    "INTEGRATION_CLICKFUNNELS_DESCRIPTION": "Agregue comentarios en vivo o chat a sus cursos de ClickFunnels.",
    "INTEGRATION_THRIVECART_LABEL": "ThriveCart Aprende+",
    "INTEGRATION_THRIVECART_DESCRIPTION": "Agregue comentarios en vivo a sus cursos ThriveCart Learn+.",
    "INTEGRATION_WEEBLY_LABEL": "Weebly",
    "INTEGRATION_WEEBLY_DESCRIPTION": "Añade comentarios en vivo a tu sitio Weebly.",
    "INTEGRATION_WEBFLOW_LABEL": "Flujo web",
    "INTEGRATION_WEBFLOW_DESCRIPTION": "Agregue comentarios en vivo a su sitio Webflow.",
    "INTEGRATION_WEBNODE_LABEL": "Nodo web",
    "INTEGRATION_WEBNODE_DESCRIPTION": "Añade comentarios en vivo a tu sitio Webnode.",
    "INTEGRATION_WOOCOMMERCE_LABEL": "WooCommerce",
    "INTEGRATION_WOOCOMMERCE_DESCRIPTION": "Agregue comentarios en vivo a sus páginas de productos de WooCommerce.",
    "INTEGRATION_SHOPIFY_LABEL": "Shopify",
    "INTEGRATION_SHOPIFY_DESCRIPTION": "Incruste comentarios directamente en las páginas de su tienda.",
    "INTEGRATION_MEMBERSPACE_LABEL": "Espacio para miembros",
    "INTEGRATION_MEMBERSPACE_DESCRIPTION": "Integre nuestro sistema de comentarios con MemberSpace.",
    "INTEGRATION_MEMBERSTACK_LABEL": "Pila de miembros",
    "INTEGRATION_MEMBERSTACK_DESCRIPTION": "Integre nuestro sistema de comentarios con Memberstack.",
    "INTEGRATION_MOODLE_LABEL": "Moodle",
    "INTEGRATION_MOODLE_DESCRIPTION": "Añadir comentarios en vivo a los cursos Moodle.",
    "INTEGRATION_GHOST_LABEL": "Fantasma",
    "INTEGRATION_GHOST_DESCRIPTION": "Añade comentarios en vivo a tu configuración de Ghost.",
    "INTEGRATION_GITHUB_PAGES_LABEL": "Páginas de GitHub",
    "INTEGRATION_GITHUB_PAGES_DESCRIPTION": "Agregue comentarios en vivo a los sitios alojados por GitHub Pages.",
    "INTEGRATION_GOHIGHLEVEL_LABEL": "GoHighLevel",
    "INTEGRATION_GOHIGHLEVEL_DESCRIPTION": "Agregue comentarios en vivo a los sitios GoHighLevel.",
    "INTEGRATION_GOOGLE_SITES_LABEL": "Sitios de Google",
    "INTEGRATION_GOOGLE_SITES_DESCRIPTION": "Agregue comentarios en vivo a los sitios alojados por Google.",
    "INTEGRATION_HOSTINGER_LABEL": "Hostinger",
    "INTEGRATION_HOSTINGER_DESCRIPTION": "Agregue comentarios en vivo a los sitios alojados por Hostinger.",
    "INTEGRATION_NOTION_LABEL": "Noción",
    "INTEGRATION_NOTION_DESCRIPTION": "Añadir comentarios en vivo a los documentos de Notion.",
    "INTEGRATION_NIMBUS_NOTE_LABEL": "Nota Nimbus",
    "INTEGRATION_NIMBUS_NOTE_DESCRIPTION": "Añade comentarios en vivo a Nimbus Note.",
    "INTEGRATION_TYPEFLO_LABEL": "Typeflo.io",
    "INTEGRATION_TYPEFLO_DESCRIPTION": "Añade comentarios en vivo a los blogs de Typeflo.",
    "INTEGRATION_ZYRO_LABEL": "Zyro",
    "INTEGRATION_ZYRO_DESCRIPTION": "Agregue comentarios en vivo a los sitios alojados por Zyro.",
    "FRAMEWORK_VANILLA_JS_LABEL": "Vainilla JS",
    "FRAMEWORK_VANILLA_JS_DESCRIPTION": "La forma más común de instalar FastComments.",
    "FRAMEWORK_ANGULAR_LABEL": "Angular",
    "FRAMEWORK_ANGULAR_DESCRIPTION": "Utilice nuestra biblioteca Angular.",
    "FRAMEWORK_REACT_LABEL": "Reaccionar",
    "FRAMEWORK_REACT_DESCRIPTION": "Utilice nuestra biblioteca React.",
    "FRAMEWORK_REACT_NATIVE_LABEL": "Reaccionar nativo",
    "FRAMEWORK_REACT_NATIVE_DESCRIPTION": "Utilice nuestra biblioteca React Native.",
    "FRAMEWORK_VUE_LABEL": "VueJS",
    "FRAMEWORK_VUE_DESCRIPTION": "Utilice nuestra biblioteca Vue.",
    "BACKEND_NODEJS_LABEL": "NodeJS",
    "BACKEND_NODEJS_DESCRIPTION": "Vea ejemplos de SSO de NodeJS.",
    "BACKEND_PHP_LABEL": "PHP",
    "BACKEND_PHP_DESCRIPTION": "Ver ejemplos de SSO en PHP.",
    "BACKEND_JAVA_LABEL": "Arranque de Java/Spring",
    "BACKEND_JAVA_DESCRIPTION": "Consulte ejemplos de SSO de Java."
}