{
    "COMMENT_MARK_NOT_REVIEWED": "Označi kot ni pregledano",
    "COMMENT_MARK_NOT_REVIEWED_TITLE": "Ste to pomotoma ocenili? Lahko označite kot nepregledano.",
    "COMMENT_MARK_REVIEWED": "Mark Reviewed",
    "COMMENT_MARK_REVIEWED_TITLE": "To lahko uporabite za filtriranje pregledanih komentarjev.",
    "COMMENT_MARK_NOT_APPROVED": "Označi kot neodobreno",
    "COMMENT_MARK_NOT_APPROVED_TITLE": "Označi kot neodobreno. S tem bo komentar skrit.",
    "COMMENT_MARK_APPROVED": "Označi kot odobreno",
    "COMMENT_MARK_APPROVED_TITLE": "Odobri ta komentar.",
    "COMMENT_MARK_AS_SPAM": "Označi kot neželeno pošto",
    "COMMENT_MARK_AS_SPAM_TITLE": "Komentar ne bo javno prikazan, če bo označen kot neželena pošta.",
    "COMMENT_MARK_NOT_SPAM": "Označi kot neželeno pošto",
    "COMMENT_MARK_NOT_SPAM_TITLE": "Komentar bo javno prikazan, če bo označen kot neželena pošta.",
    "COMMENT_EDIT": "Uredi",
    "COMMENT_DELETE": "Izbriši",
    "COMMENT_BAN": "Prepoved",
    "COMMENT_VIEW_ALL_FROM_IP": "Ogled vseh iz IP-ja",
    "COMMENT_UN_FLAG": "Odstrani zastavo",
    "COMMENT_AWARD_BADGE": "Značka za nagrado",
    "COMMENT_REMOVE_BADGE": "Odstrani značko",
    "COMMENT_UNVERIFIED_NOTICE": "Nepreverjen komentar",
    "COMMENT_DELETED": "Izbrisano",
    "COMMENT_DELETED_TEXT": "Izbrisan komentar.",
    "COMMENT_THUMBS_UP": "palec gor",
    "COMMENT_VIEW_LOGS": "Ogled dnevnikov",
    "COMMENT_REPLIES": "Odgovori",
    "COMMENT_REPLY": "Odgovori",
    "COMMENT_VIEW_COMMENT": "Ogled komentarja",
    "COMMENT_ON": "na",
    "COMMENT_AVATAR_ALT": "Avatar",
    "COMMENT_AVATAR_TITLE": "Avatar"
}