{
    "PAGE_TITLE": "Desactivar la adición automática de dominios - FastComments",
    "HEADING_RE_ENABLE_AUTOMATIC_DOMAIN_ADDING": "Volver a habilitar la adición automática de dominios",
    "HEADING_DISABLING_AUTOMATIC_DOMAIN_ADDING": "Deshabilitar la adición automática de dominios",
    "TEXT_RE_ENABLE_CONFIRM": "Estás a punto de reactivar la adición automática de dominios a tu cuenta. ¿Quieres continuar?",
    "TEXT_DISABLE_CONFIRM": "Estás a punto de desactivar la adición automática de dominios a tu cuenta. ¿Continuar?",
    "TEXT_WHITELIST_NOTE": "<b>Tenga en cuenta</b> que muchos sitios, plataformas y bots están en la lista blanca, por lo que no se añadirán a su cuenta. Si cree que un sitio o plataforma muy común se añadió a su cuenta y debería estar en la lista blanca, infórmenos para que podamos mejorar FastComments.",
    "BUTTON_CANCEL": "Cancelar",
    "BUTTON_ENABLE_AUTOMATIC_DOMAIN_ADDING": "Habilitar la adición automática de dominios",
    "BUTTON_DISABLE_AUTOMATIC_DOMAIN_ADDING": "Deshabilitar la adición automática de dominios"
}