{
    "STEP_LABEL": "Корак 1 од 3",
    "PAGE_TITLE": "Повежи се са Shopify-ом - Брзи коментари",
    "HEADING": "Повежите своју Shopify продавницу",
    "META_DESCRIPTION": "Повежите своју Shopify продавницу са FastComments-ом.",
    "DESCRIPTION": "Додајте коментаре уживо и ћаскајте у своју Shopify продавницу за неколико минута. Хајде да повежемо вашу продавницу са FastComments налогом.",
    "HAVE_ACCOUNT_HEADING": "Да ли имате налог на FastComments-у?",
    "SHOP_DOMAIN_LABEL": "Ваша продавница",
    "ERROR_MISSING_SHOP": "Недостају подаци о продавници. Молимо вас покушајте поново са Shopify-а.",
    "BUTTON_LOGIN": "Да, пријави ме",
    "BUTTON_SIGNUP": "Не, креирај налог",
    "ERROR_INVALID_HMAC": "Потпис захтева је неважећи. Молимо покушајте поново са Shopify-а."
}