{
    "PAGE_TITLE": "FastComments - ¡Bienvenido!",
    "HEADING_WELCOME": "¡Bienvenido!",
    "HEADING_SUCCESS": "¡Su cuenta fue creada exitosamente!",
    "WORDPRESS_DESCRIPTION": "Parece que tu sitio web funciona con WordPress. Tenemos un plugin de WordPress que facilita la configuración de FastComments. Además, migra tus comentarios existentes.",
    "BUTTON_GET_PLUGIN": "Obtener el complemento de WordPress",
    "BUTTON_MY_ACCOUNT": "Ir a Mi cuenta",
    "BUTTON_READ_DOCS": "Lea los documentos",
    "INSTALLATION_WIZARD_VIEWING_FOR": "Instrucciones de visualización para <%= wizard.productName %>.",
    "INSTALLATION_WIZARD_CHANGE": "Cambiar."
}