{
    "PAGE_TITLE": "ביטול מנוי - FastComments",
    "HEADING_CANCEL_SUBSCRIPTION": "ביטול מנוי עבור: <%= tenant.name %>",
    "TEXT_ACCOUNT_OWNER_WARNING": "אתה בעל חשבון. פעולה זו תבטל את המנוי לחשבון.",
    "HEADING_CONFIRMATION": "אִשׁוּר",
    "LABEL_CONFIRM_CHECKBOX": "סמן תיבה זו כדי לאשר את ביטול המנוי שלך. באפשרותך להפעיל מחדש את חשבונך בכל עת.",
    "LABEL_FEEDBACK": "מה נוכל לעשות טוב יותר?",
    "BUTTON_NO_DONT_CANCEL": "לא, אל תבטלו את המנוי שלי",
    "BUTTON_YES_CANCEL": "כן, בטל את המנוי שלי"
}