{
    "PAGE_TITLE": "Надіслані електронні листи - FastComments",
    "HEADING": "Надіслані електронні листи",
    "INFO_NOTE": "<strong>Примітка:</strong> Історію електронної пошти ми зберігаємо лише два місяці. Старіші листи автоматично видаляються.",
    "LABEL_FILTER_SUBJECT": "Фільтрувати за темою",
    "PLACEHOLDER_SUBJECT": "Пошук по темі...",
    "LABEL_FILTER_CONTENT": "Фільтрувати за вмістом",
    "PLACEHOLDER_CONTENT": "Пошук вмісту електронної пошти...",
    "BUTTON_SEARCH": "Пошук",
    "BUTTON_CLEAR": "Очистити",
    "TABLE_HEADER_DATE": "Дата",
    "TABLE_HEADER_FROM": "Від",
    "TABLE_HEADER_SUBJECT": "Тема",
    "MESSAGE_NO_EMAILS_FILTERS": "За вказаними фільтрами не знайдено електронних листів.",
    "BUTTON_VIEW": "Переглянути",
    "BUTTON_PREV": "Попередній",
    "BUTTON_NEXT": "Далі",
    "LABEL_PAGE": "Сторінка <%= page %>",
    "MESSAGE_NO_EMAILS": "У вас немає надісланих електронних листів.",
    "VALUE_UNKNOWN": "Невідомо",
    "VALUE_NO_SUBJECT": "(Без теми)",
    "VALUE_NA": "Немає даних"
}