{
    "HEADING": "Sve je spremno!",
    "META_DESCRIPTION": "Vaša Shopify prodavnica je povezana sa FastComments-om.",
    "COPY_BUTTON": "Kopiraj",
    "TENANT_ID_LABEL": "Vaš ID zakupca",
    "PAGE_TITLE": "Sve je spremno - FastComments",
    "COPIED_BUTTON": "Kopirano!",
    "STEP_LABEL": "Korak 3 od 3",
    "HOW_TO_HEADING": "Kako dodati komentare u vašu prodavnicu",
    "HOW_TO_STEP_4": "Sačuvajte i objavite. Komentari su uživo! Prijavljeni kupci se automatski identifikuju putem SSO-a.",
    "SETTINGS_LINK_TEXT": "Podešavanja → API / SSO",
    "BUTTON_MANAGE_SUBSCRIPTION": "Upravljanje pretplatom",
    "DESCRIPTION": "Vaša Shopify prodavnica je sada povezana sa FastComments-om. Poslednja stvar: kopirajte svoj ID zakupca u Shopify blokove teme.",
    "HOW_TO_STEP_3": "Dodajte <b>FastComments</b> blok i nalepite <b>svoj ID zakupca</b> u podešavanja bloka",
    "FIND_LATER_NOTE": "Uvek možete kasnije pronaći svoj ID zakupca na",
    "BUTTON_SUBSCRIBE": "Započnite pretplatu",
    "HOW_TO_STEP_2": "Kliknite <b>Dodaj odeljak</b>, a zatim pogledajte pod <b>Apps</b> da pronađete blokove FastComments",
    "HOW_TO_STEP_1": "Otvorite Shopify administraciju i idite na <b>Online Store → Themes → Customize</b>",
    "BUTTON_ACCOUNT_HOME": "Početna naloga",
    "BUTTON_MODERATE": "Moderiraj",
    "BUTTON_ADD_USERS": "Dodaj korisnike",
    "BUTTON_CUSTOMIZE": "Prilagodi",
    "HOW_TO_STEP_5": "Istražite dodatne vidžete kao što su <b>Nedavni komentari</b>, <b>Nedavne diskusije</b>, <b>Glavne stranice</b> i <b>Broj komentara</b>"
}